qmllib/__init__.py
qmllib/version.py
qmllib/constants/__init__.py
qmllib/constants/periodic_table.py
qmllib/kernels/__init__.py
qmllib/kernels/distance.py
qmllib/kernels/fdistance.cpython-312-x86_64-linux-gnu.so
qmllib/kernels/fdistance.f90
qmllib/kernels/fgradient_kernels.cpython-312-x86_64-linux-gnu.so
qmllib/kernels/fgradient_kernels.f90
qmllib/kernels/fkernels.cpython-312-x86_64-linux-gnu.so
qmllib/kernels/fkernels.f90
qmllib/kernels/fkpca.f90
qmllib/kernels/gradient_kernels.py
qmllib/kernels/kernels.py
qmllib/kernels/wrappers.py
qmllib/representations/__init__.py
qmllib/representations/facsf.cpython-312-x86_64-linux-gnu.so
qmllib/representations/facsf.f90
qmllib/representations/frepresentations.cpython-312-x86_64-linux-gnu.so
qmllib/representations/frepresentations.f90
qmllib/representations/fslatm.cpython-312-x86_64-linux-gnu.so
qmllib/representations/fslatm.f90
qmllib/representations/representations.py
qmllib/representations/slatm.py
qmllib/representations/arad/__init__.py
qmllib/representations/arad/arad.py
qmllib/representations/arad/farad_kernels.cpython-312-x86_64-linux-gnu.so
qmllib/representations/bob/__init__.py
qmllib/representations/fchl/__init__.py
qmllib/representations/fchl/fchl_electric_field_kernels.py
qmllib/representations/fchl/fchl_force_kernels.py
qmllib/representations/fchl/fchl_kernel_functions.py
qmllib/representations/fchl/fchl_representations.py
qmllib/representations/fchl/fchl_scalar_kernels.py
qmllib/representations/fchl/ffchl_electric_field_kernels.f90
qmllib/representations/fchl/ffchl_force_kernels.f90
qmllib/representations/fchl/ffchl_kernel_types.f90
qmllib/representations/fchl/ffchl_kernels.f90
qmllib/representations/fchl/ffchl_module.cpython-312-x86_64-linux-gnu.so
qmllib/representations/fchl/ffchl_module.f90
qmllib/representations/fchl/ffchl_scalar_kernels.f90
qmllib/solvers/Makefile
qmllib/solvers/__init__.py
qmllib/solvers/fsolvers.cpython-312-x86_64-linux-gnu.so
qmllib/solvers/fsolvers.f90
qmllib/utils/__init__.py
qmllib-1.0.0.dist-info/LICENSE
qmllib-1.0.0.dist-info/METADATA
qmllib-1.0.0.dist-info/WHEEL
qmllib-1.0.0.dist-info/top_level.txt
qmllib-1.0.0.dist-info/RECORD
