Metadata-Version: 2.1
Name: qmllib
Version: 1.0.0
Project-URL: Homepage, https://qmlcode.org
Keywords: qml,quantum chemistry,machine learning
Classifier: License :: OSI Approved :: MIT License
Classifier: Programming Language :: Python
Classifier: Programming Language :: Python :: 3
Requires-Python: >=3.12
License-File: LICENSE
Requires-Dist: numpy
Requires-Dist: scipy
